sha_assist.py
sha_assist-0.1.1.dist-info/LICENSE
sha_assist-0.1.1.dist-info/WHEEL
sha_assist-0.1.1.dist-info/METADATA
sha_assist-0.1.1.dist-info/RECORD
