Metadata-Version: 2.1
Name: sha-assist
Version: 0.1.1
Summary: Easy SHA1, SHA256, SHA384, SHA512 and MD5 HTTPS domain fingerprinting
Home-page: https://github.com/AndrewGlago/sha-assist
License: MIT
Author: AndrewGlago
Author-email: andrewglago1@gmail.com
Requires-Python: >=3.8,<4.0
Classifier: License :: OSI Approved :: MIT License
Classifier: Programming Language :: Python :: 3
Classifier: Programming Language :: Python :: 3.8
Classifier: Programming Language :: Python :: 3.9
Requires-Dist: click (>=8.0.1,<9.0.0)
Project-URL: Repository, https://github.com/AndrewGlago/sha-assist
